Workbook

Sheet ORDER LOG
A1: Date Added | B1: Order # | C1: Order Date | D1: Client Name | E1: Client Phone | F1: Client Email | G1: Referred By | H1: Service Type | I1: Pickup Address | J1: Delivery Address | K1: Item Description | L1: Pickup Date | M1: Pickup Time | N1: Delivery Attempt | O1: Reschedule | P1: Reschedule Fee | Q1: Base Rate | R1: Rush Fee | S1: Extra Stop | T1: Extra Stop Fee | U1: Extended Area Fee | V1: Discount Type | W1: Discount Amount | X1: Total Trip Cost | Y1: Booking Fee Paid | Z1: Balance Before Adjustments | AA1: Final Balance Due | AB1: Order Status | AC1: Date Paid | AD1: Payment Method | AE1: Receipt Provided | AF1: Refund Amount | AG1: Referral Credit Earned (Referrer) | AH1: Referral Credit Earned (Referred) | AI1: Referral Credit Used | AJ1: Total Paid Orders | AK1: Loyalty Used | AL1: Loyalty Available | AM1: Loyalty READY | AN1: Notes
P2: =IF(O2="Yes",10,0) | T2: =IF(S2="Yes",10,0) | X2: =Q2+R2+T2+U2-W2 | Z2: =X2-Y2 | AA2: =Z2+P2

Sheet PRINT VIEW
A1: Select Order #:
A3: Order # | B3: =IFERROR(VLOOKUP($B$1,'ORDER LOG'!$B$2:$AN$500,1,FALSE),"")
A4: Client Name | B4: =IFERROR(VLOOKUP($B$1,'ORDER LOG'!$B$2:$AN$500,2,FALSE),"")
A5: Pickup Address | B5: =IFERROR(VLOOKUP($B$1,'ORDER LOG'!$B$2:$AN$500,3,FALSE),"")
A6: Delivery Address | B6: =IFERROR(VLOOKUP($B$1,'ORDER LOG'!$B$2:$AN$500,4,FALSE),"")
A7: Item Description | B7: =IFERROR(VLOOKUP($B$1,'ORDER LOG'!$B$2:$AN$500,5,FALSE),"")
A8: Service Type | B8: =IFERROR(VLOOKUP($B$1,'ORDER LOG'!$B$2:$AN$500,6,FALSE),"")
A9: Base Rate | B9: =IFERROR(VLOOKUP($B$1,'ORDER LOG'!$B$2:$AN$500,7,FALSE),"")
A10: Rush Fee | B10: =IFERROR(VLOOKUP($B$1,'ORDER LOG'!$B$2:$AN$500,8,FALSE),"")
A11: Extra Stop Fee | B11: =IFERROR(VLOOKUP($B$1,'ORDER LOG'!$B$2:$AN$500,9,FALSE),"")
A12: Extended Area Fee | B12: =IFERROR(VLOOKUP($B$1,'ORDER LOG'!$B$2:$AN$500,10,FALSE),"")
A13: Discount Type | B13: =IFERROR(VLOOKUP($B$1,'ORDER LOG'!$B$2:$AN$500,11,FALSE),"")
A14: Discount Amount | B14: =IFERROR(VLOOKUP($B$1,'ORDER LOG'!$B$2:$AN$500,12,FALSE),"")
A15: Total Trip Cost | B15: =IFERROR(VLOOKUP($B$1,'ORDER LOG'!$B$2:$AN$500,13,FALSE),"")
A16: Booking Fee Paid | B16: =IFERROR(VLOOKUP($B$1,'ORDER LOG'!$B$2:$AN$500,14,FALSE),"")
A17: Reschedule Fee | B17: =IFERROR(VLOOKUP($B$1,'ORDER LOG'!$B$2:$AN$500,15,FALSE),"")
A18: Final Balance Due | B18: =IFERROR(VLOOKUP($B$1,'ORDER LOG'!$B$2:$AN$500,16,FALSE),"")
A19: Order Status | B19: =IFERROR(VLOOKUP($B$1,'ORDER LOG'!$B$2:$AN$500,17,FALSE),"")
A20: Date Paid | B20: =IFERROR(VLOOKUP($B$1,'ORDER LOG'!$B$2:$AN$500,18,FALSE),"")
A21: Payment Method | B21: =IFERROR(VLOOKUP($B$1,'ORDER LOG'!$B$2:$AN$500,19,FALSE),"")
A22: Refund Amount | B22: =IFERROR(VLOOKUP($B$1,'ORDER LOG'!$B$2:$AN$500,20,FALSE),"")
A23: Referral Earned (Referrer) | B23: =IFERROR(VLOOKUP($B$1,'ORDER LOG'!$B$2:$AN$500,21,FALSE),"")
A24: Referral Earned (Referred) | B24: =IFERROR(VLOOKUP($B$1,'ORDER LOG'!$B$2:$AN$500,22,FALSE),"")
A25: Referral Used | B25: =IFERROR(VLOOKUP($B$1,'ORDER LOG'!$B$2:$AN$500,23,FALSE),"")
A26: Loyalty READY | B26: =IFERROR(VLOOKUP($B$1,'ORDER LOG'!$B$2:$AN$500,24,FALSE),"")
A27: Notes | B27: =IFERROR(VLOOKUP($B$1,'ORDER LOG'!$B$2:$AN$500,25,FALSE),"")
